Workbook

Sheet Executive Dashboard
B2: EBM CLIENTS - EXECUTIVE CRM DASHBOARD
B3: Real-time pipeline metrics & outreach performance from 'Lead Pipeline' tab
B5: Total Leads | D5: Uncontacted | F5: Contacted / In Progress | H5: Won / Deals Closed
B6: =COUNTA('Lead Pipeline'!A5:A34) | D6: =COUNTIF('Lead Pipeline'!O5:O34, "1. Uncontacted") | F6: =COUNTIF('Lead Pipeline'!O5:O34, "2. Contacted") + COUNTIF('Lead Pipeline'!O5:O34, "3. Meeting Pitched") + COUNTIF('Lead Pipeline'!O5:O34, "4. Proposal Sent") | H6: =COUNTIF('Lead Pipeline'!O5:O34, "5. Closed - Won")
B9: Lead Status Breakdown | F9: Industry Category Breakdown
B10: Pipeline Stage | C10: Lead Count | D10: Share (%) | F10: Industry | G10: Count | H10: Share (%)
B11: 1. Uncontacted | C11: =COUNTIF('Lead Pipeline'!O$5:O$34, B11) | D11: =C11/$C$17 | F11: Locks & Hardware | G11: =COUNTIF('Lead Pipeline'!E$5:E$34, F11) | H11: =G11/$G$16
B12: 2. Contacted | C12: =COUNTIF('Lead Pipeline'!O$5:O$34, B12) | D12: =C12/$C$17 | F12: Healthcare & Hospitals | G12: =COUNTIF('Lead Pipeline'!E$5:E$34, F12) | H12: =G12/$G$16
B13: 3. Meeting Pitched | C13: =COUNTIF('Lead Pipeline'!O$5:O$34, B13) | D13: =C13/$C$17 | F13: Logistics & Transport | G13: =COUNTIF('Lead Pipeline'!E$5:E$34, F13) | H13: =G13/$G$16
B14: 4. Proposal Sent | C14: =COUNTIF('Lead Pipeline'!O$5:O$34, B14) | D14: =C14/$C$17 | F14: Hospitality & Hotels | G14: =COUNTIF('Lead Pipeline'!E$5:E$34, F14) | H14: =G14/$G$16
B15: 5. Closed - Won | C15: =COUNTIF('Lead Pipeline'!O$5:O$34, B15) | D15: =C15/$C$17 | F15: Chemical & Pharma | G15: =COUNTIF('Lead Pipeline'!E$5:E$34, F15) | H15: =G15/$G$16
B16: 6. Closed - Lost | C16: =COUNTIF('Lead Pipeline'!O$5:O$34, B16) | D16: =C16/$C$17 | F16: Total | G16: =SUM(G11:G15) | H16: =SUM(H11:H15)
B17: Total | C17: =SUM(C11:C16) | D17: =SUM(D11:D16)
B19: HOW TO USE THIS WORKBOOK:
B20: 1. Go to the 'Lead Pipeline' tab to see all 30 enriched company accounts with email, website, and addresses.
B21: 2. Click the 'WhatsApp Direct' link in column R to immediately chat with decision makers.
B22: 3. Click the 'Website' link in column I to inspect each company's product catalog before calling.
B23: 4. Use the dropdown in 'Status' (Col O) and 'Priority' (Col P) to track your interaction stages.
B24: 5. Check the 'Outreach Scripts & Guides' tab for ready-to-use Email, SMS, Call, and LinkedIn templates.

Sheet Lead Pipeline
A1: EBM CLIENTS - ACTIVE ENRICHED OUTREACH PIPELINE
A2: Master list of 30 prospective accounts with contact intelligence, verified decision makers, emails, and EBM pitches
A4: Rank | B4: Company Name | C4: Operating Brand | D4: Decision Maker | E4: Industry Category | F4: Primary Mobile / WA | G4: Office Phone | H4: Email Address | I4: Official Website | J4: Aligarh Address | K4: Products / Offerings | L4: EBM Pitch Opportunity | M4: Identified Pain Point | N4: Outreach Hook | O4: Status | P4: Priority | Q4: Last Contact Date | R4: WhatsApp Direct | S4: Next Follow-up | T4: Notes & Objections
A5: 1 | B5: DUKE LOCKS | C5: Duke Locks (Adarsh Industries) | D5: Pramod Kumar (Management - Adarsh Industries) | E5: Locks & Hardware | F5: +91 99996 26676 | G5: +91 571 2780166 / +91 98374 29009 | H5: =HYPERLINK("mailto:info@dukelocks.in", "info@dukelocks.in") | I5: =HYPERLINK("https://dukelocks.in", "dukelocks.in") | J5: C-226, Sector-2, Tala Nagri, Ramghat Road, Aligarh - 202001, UP | K5: Mortice locks, main door locks, shutter locks, cupboard locks, door hardware | L5: Dealer CRM + sales automation + digital catalog & distributor portal | M5: Managing a large dealer distribution network manually across North India with delayed order updates | N5: Automate dealer re-orders, digital catalog sharing on WhatsApp, and trade portal lead centralization. | O5: 1. Uncontacted | P5: High | R5: =HYPERLINK("https://wa.me/919999626676?text=Namaste%20Pramod%20Kumar%2C%20Badal%20here%20from%20EBM%20Solutions%20Aligarh.%20Regarding%20DUKE%20LOCKS%3A%20we%20specialize%20in%20Dealer%20CRM%20%2B%20sales%20automation%20%2B%20digital%20catalog%20%26%20distributor%20portal.%20Would%20you%20be%20open%20for%20a%20quick%205-min%20discussion%20this%20week%3F%20%28Reply%20STOP%20to%20opt%20out%29", "💬 Chat on WhatsApp")
A6: 2 | B6: EURO INDIA | C6: Euro India Architectural Hardware | D6: Sachin Garg (Managing Director) | E6: Locks & Hardware | F6: +91 95944 81782 | G6: +91 88817 80603 | H6: =HYPERLINK("mailto:info@euroindia.in", "info@euroindia.in") | I6: =HYPERLINK("https://euroindia.in", "euroindia.in") | J6: A-9, Sector-1, Talanagri, Ramghat Road, Aligarh - 202001, UP | K6: Architectural hardware, premium mortise handles, pull handles, aldrops, brass fittings | L6: B2B CRM + dealer management + interactive digital catalogue | M6: Architecture and interior design leads need high-resolution interactive catalogs and prompt quote generation | N6: Enable instant PDF/digital brochure delivery over WhatsApp and direct architect lead tracking. | O6: 1. Uncontacted | P6: High | R6: =HYPERLINK("https://wa.me/919594481782?text=Namaste%20Sachin%20Garg%2C%20Badal%20here%20from%20EBM%20Solutions%20Aligarh.%20Regarding%20EURO%20INDIA%3A%20we%20specialize%20in%20B2B%20CRM%20%2B%20dealer%20management%20%2B%20interactive%20digital%20catalogue.%20Would%20you%20be%20open%20for%20a%20quick%205-min%20discussion%20this%20week%3F%20%28Reply%20STOP%20to%20opt%20out%29", "💬 Chat on WhatsApp")
A7: 3 | B7: Atom Lock (Wolf Enterprises) - Manufacturer in Aligarh | C7: Atom Lock (Wolf Enterprises) | D7: Naveen Brijwasi (Founder & CEO) | E7: Locks & Hardware | F7: +91 94122 73735 | G7: +91 571 2780300 | H7: =HYPERLINK("mailto:info@atomlock.in", "info@atomlock.in") | I7: =HYPERLINK("https://atomlock.in", "atomlock.in") | J7: Talanagri Industrial Area, Ramghat Road, Aligarh - 202001, UP | K7: Smart door locks, mortise door locks, digital locks, cabinet handles, door closers (46+ categories) | L7: AI sales automation + multi-channel CRM + distributor order portal | M7: Fast-growing brand scaling across e-commerce (Amazon/Flipkart) and offline retail simultaneously | N7: Centralize multi-channel buyer inquiries and automate dealer warranty and after-sales tickets. | O7: 1. Uncontacted | P7: High | R7: =HYPERLINK("https://wa.me/919412273735?text=Namaste%20Naveen%20Brijwasi%2C%20Badal%20here%20from%20EBM%20Solutions%20Aligarh.%20Regarding%20Atom%20Lock%20%28Wolf%20Enterprises%29%20-%20Manufacturer%20in%20Aligarh%3A%20we%20specialize%20in%20AI%20sales%20automation%20%2B%20multi-channel%20CRM%20%2B%20distributor%20order%20portal.%20Would%20you%20be%20open%20for%20a%20quick%205-min%20discussion%20this%20week%3F%20%28Reply%20STOP%20to%20opt%20out%29", "💬 Chat on WhatsApp")
A8: 4 | B8: EURO INDIA - Manufacturer of Architectural Hardware | C8: Euro India Hardware Division | D8: Director of Sales & Distribution | E8: Locks & Hardware | F8: +91 95944 81782 | G8: +91 88817 80603 | H8: =HYPERLINK("mailto:customercare@euroindia.in", "customercare@euroindia.in") | I8: =HYPERLINK("https://euroindia.in", "euroindia.in") | J8: A-9, Sector-1, Talanagri, Ramghat Road, Aligarh - 202001, UP | K8: Commercial project door hardware, brass pull handles, locks, tower bolts | L8: Dealer CRM + project quote automation + dispatch analytics | M8: Quotations for bulk building contractors take days to compute and follow up manually | N8: Automated pricing matrix & CRM to close builder project quotes 3x faster. | O8: 1. Uncontacted | P8: High | R8: =HYPERLINK("https://wa.me/919594481782?text=Namaste%20Director%20of%20Sales%20%26%20Distribution%2C%20Badal%20here%20from%20EBM%20Solutions%20Aligarh.%20Regarding%20EURO%20INDIA%20-%20Manufacturer%20of%20Architectural%20Hardware%3A%20we%20specialize%20in%20Dealer%20CRM%20%2B%20project%20quote%20automation%20%2B%20dispatch%20analytics.%20Would%20you%20be%20open%20for%20a%20quick%205-min%20discussion%20this%20week%3F%20%28Reply%20STOP%20to%20opt%20out%29", "💬 Chat on WhatsApp")
A9: 5 | B9: Ashoka Locks | C9: Ashoka Locks | D9: Ashish Agarwal (Director / Proprietor) | E9: Locks & Hardware | F9: +91 98975 47024 | G9: +91 571 3551364 | H9: =HYPERLINK("mailto:ashish@ashokalocks.com", "ashish@ashokalocks.com") | I9: =HYPERLINK("https://ashokalocks.com", "ashokalocks.com") | J9: 5/84, Opp. Purnagiri Temple, I.T.I. Road, Aligarh - 202001, UP | K9: Industrial hardware, quarter-turn locks, canopy locks, compression locks, hinges & handles | L9: Export CRM + AI enquiry automation + B2B quote pipeline | M9: Inquiries from IndiaMART, website, and export portals take too long to answer manually | N9: Instant 24/7 WhatsApp catalogue response for incoming B2B buyer leads. | O9: 1. Uncontacted | P9: High | R9: =HYPERLINK("https://wa.me/919897547024?text=Namaste%20Ashish%20Agarwal%2C%20Badal%20here%20from%20EBM%20Solutions%20Aligarh.%20Regarding%20Ashoka%20Locks%3A%20we%20specialize%20in%20Export%20CRM%20%2B%20AI%20enquiry%20automation%20%2B%20B2B%20quote%20pipeline.%20Would%20you%20be%20open%20for%20a%20quick%205-min%20discussion%20this%20week%3F%20%28Reply%20STOP%20to%20opt%20out%29", "💬 Chat on WhatsApp")
A10: 6 | B10: Yamuna Exports | C10: Yamuna Exports | D10: Pawan Kumar (Proprietor) | E10: Locks & Hardware | F10: +91 99270 14542 | G10: +91 92196 16689 | H10: =HYPERLINK("mailto:info@yamunaexports.com", "info@yamunaexports.com") | I10: =HYPERLINK("http://www.yamunaexports.com", "yamunaexports.com") | J10: C-92, Sector-1, UPSIDC, Talanagri Industrial Estate, Ramghat Road, Aligarh - 202001, UP | K10: Architectural hardware, door knobs, window locks, designer bell pushes, brass & stainless fittings | L10: Export CRM + production/dispatch dashboard + multi-currency quotation system | M10: Export buyers across US/Europe require immediate spec sheets, sample tracking, and shipment milestones | N10: Streamline export sampling, proforma invoice follow-ups, and international buyer communications. | O10: 1. Uncontacted | P10: High | R10: =HYPERLINK("https://wa.me/919927014542?text=Namaste%20Pawan%20Kumar%2C%20Badal%20here%20from%20EBM%20Solutions%20Aligarh.%20Regarding%20Yamuna%20Exports%3A%20we%20specialize%20in%20Export%20CRM%20%2B%20production/dispatch%20dashboard%20%2B%20multi-currency%20quotation%20system.%20Would%20you%20be%20open%20for%20a%20quick%205-min%20discussion%20this%20week%3F%20%28Reply%20STOP%20to%20opt%20out%29", "💬 Chat on WhatsApp")
A11: 7 | B11: Laxmi Locks India | C11: Laxmi Locks India (Laxmi Udyog) | D11: Karan Agrawal (Partner / Director) | E11: Locks & Hardware | F11: +91 98379 94940 | G11: +91 571 2400325 | H11: =HYPERLINK("mailto:laxmiudyog@gmail.com", "laxmiudyog@gmail.com") | I11: =HYPERLINK("https://laxmilocksindia.com", "laxmilocksindia.com") | J11: 8/4 A, Johnson Compound, Jail Road, Aligarh - 202001, UP | K11: Heritage mortise locks, padlocks, iron/brass hardware (established 1957) | L11: Digital catalogue + dealer re-ordering portal + modern B2B lead CRM | M11: Traditional legacy brand needing to digitize its distributor communications and order logging | N11: Upgrade dealer phone ordering into a seamless mobile WhatsApp catalog system. | O11: 1. Uncontacted | P11: High | R11: =HYPERLINK("https://wa.me/919837994940?text=Namaste%20Karan%20Agrawal%2C%20Badal%20here%20from%20EBM%20Solutions%20Aligarh.%20Regarding%20Laxmi%20Locks%20India%3A%20we%20specialize%20in%20Digital%20catalogue%20%2B%20dealer%20re-ordering%20portal%20%2B%20modern%20B2B%20lead%20CRM.%20Would%20you%20be%20open%20for%20a%20quick%205-min%20discussion%20this%20week%3F%20%28Reply%20STOP%20to%20opt%20out%29", "💬 Chat on WhatsApp")
A12: 8 | B12: Agon / Sachin Manufacturing Company | C12: Agon Locks (Sachin Manufacturing Co.) | D12: Kanti Kumar Agrawal / Praveen Agrawal / Akash Agrawal | E12: Locks & Hardware | F12: +91 92196 57850 | G12: +91 75360 08008 / +91 79063 52046 | H12: =HYPERLINK("mailto:sachinmfg@gmail.com", "sachinmfg@gmail.com") | I12: =HYPERLINK("http://www.agonlocks.com", "agonlocks.com") | J12: Rasal Ganj, Aligarh - 202001, UP | K12: Agon mortise locks, multipurpose locks, furniture locks, handles | L12: Manufacturing dashboard + dealer CRM + warranty tracking automation | M12: Multiple partners managing operations across production and retail distribution | N12: Unified dashboard tracking dealer dispatches, pending payments, and stock inquiries. | O12: 1. Uncontacted | P12: High | R12: =HYPERLINK("https://wa.me/919219657850?text=Namaste%20Kanti%20Kumar%20Agrawal%2C%20Badal%20here%20from%20EBM%20Solutions%20Aligarh.%20Regarding%20Agon%20/%20Sachin%20Manufacturing%20Company%3A%20we%20specialize%20in%20Manufacturing%20dashboard%20%2B%20dealer%20CRM%20%2B%20warranty%20tracking%20automation.%20Would%20you%20be%20open%20for%20a%20quick%205-min%20discussion%20this%20week%3F%20%28Reply%20STOP%20to%20opt%20out%29", "💬 Chat on WhatsApp")
A13: 9 | B13: Scientific Lock Industries | C13: Scientific Lock Industries | D13: Amit Kumar / Sunil Kumar (Partners) | E13: Locks & Hardware | F13: +91 94114 14164 | G13: +91 94125 95654 | H13: =HYPERLINK("mailto:scientificlocks@gmail.com", "scientificlocks@gmail.com") | I13: =HYPERLINK("https://www.indiamart.com/scientificlockindustries/", "indiamart.com") | J13: Sarai Sultani, Aligarh - 202001, UP | K13: Specialized shutter locks, brass padlocks, rim locks, cabinet security locks | L13: Order management + automated B2B lead capture + inquiry analytics | M13: High volume of wholesale inquiries from trade portals without automated capture | N13: Auto-import IndiaMART leads into CRM and trigger instant WhatsApp follow-up. | O13: 1. Uncontacted | P13: High | R13: =HYPERLINK("https://wa.me/919411414164?text=Namaste%20Amit%20Kumar%2C%20Badal%20here%20from%20EBM%20Solutions%20Aligarh.%20Regarding%20Scientific%20Lock%20Industries%3A%20we%20specialize%20in%20Order%20management%20%2B%20automated%20B2B%20lead%20capture%20%2B%20inquiry%20analytics.%20Would%20you%20be%20open%20for%20a%20quick%205-min%20discussion%20this%20week%3F%20%28Reply%20STOP%20to%20opt%20out%29", "💬 Chat on WhatsApp")
A14: 10 | B14: Locks & Locking Devices India / VIJAYAN | C14: Locks & Locking Devices India (VIJAYAN) | D14: Eshank Bansal (Director) | E14: Locks & Hardware | F14: +91 99977 77354 | G14: +91 75358 10000 / +91 98377 88111 | H14: =HYPERLINK("mailto:info@vijayanlocks.co.in", "info@vijayanlocks.co.in") | I14: =HYPERLINK("https://www.vijayanlocks.co.in", "vijayanlocks.co.in") | J14: 5/536, B-19, Agarwal Street, Shakti Nagar, Goolar Road, Aligarh - 202001, UP | K14: Vijayan cylindrical locks, mortise locksets, stainless steel architectural fittings | L14: Digital sales + CRM + export lead generation + distribution analytics | M14: Fast-moving SKU range requiring real-time inventory visibility for distributors | N14: Smart digital distributor catalog with live stock inquiry automation. | O14: 1. Uncontacted | P14: High | R14: =HYPERLINK("https://wa.me/919997777354?text=Namaste%20Eshank%20Bansal%2C%20Badal%20here%20from%20EBM%20Solutions%20Aligarh.%20Regarding%20Locks%20%26%20Locking%20Devices%20India%20/%20VIJAYAN%3A%20we%20specialize%20in%20Digital%20sales%20%2B%20CRM%20%2B%20export%20lead%20generation%20%2B%20distribution%20analytics.%20Would%20you%20be%20open%20for%20a%20quick%205-min%20discussion%20this%20week%3F%20%28Reply%20STOP%20to%20opt%20out%29", "💬 Chat on WhatsApp")
A15: 11 | B15: Lico Lock | C15: Lico Locks & Hardware | D15: Mayank Bansal (Proprietor) | E15: Locks & Hardware | F15: +91 99978 52369 | G15: +91 571 2701234 | H15: =HYPERLINK("mailto:licolocks@gmail.com", "licolocks@gmail.com") | I15: =HYPERLINK("https://licolocks.com", "licolocks.com") | J15: Industrial Area, GT Road, Aligarh - 202001, UP | K15: Brass padlocks, mortise locks, cabinet hardware, zinc handles | L15: B2B CRM + website/e-commerce + quote automation | M15: Lacks a modern interactive web catalogue to capture younger retail buyers and builders | N15: Rapid launch of high-converting product showcase site + automated lead capture. | O15: 1. Uncontacted | P15: Medium | R15: =HYPERLINK("https://wa.me/919997852369?text=Namaste%20Mayank%20Bansal%2C%20Badal%20here%20from%20EBM%20Solutions%20Aligarh.%20Regarding%20Lico%20Lock%3A%20we%20specialize%20in%20B2B%20CRM%20%2B%20website/e-commerce%20%2B%20quote%20automation.%20Would%20you%20be%20open%20for%20a%20quick%205-min%20discussion%20this%20week%3F%20%28Reply%20STOP%20to%20opt%20out%29", "💬 Chat on WhatsApp")
A16: 12 | B16: Tyler Locks & Hardware | C16: Tyler Locks (Deep Industries) | D16: Sundeep Kumar (Managing Director) | E16: Locks & Hardware | F16: +91 98971 48183 | G16: +91 99113 63525 | H16: =HYPERLINK("mailto:sales@tylerlocks.com", "sales@tylerlocks.com") | I16: =HYPERLINK("http://www.tylerlocks.com", "tylerlocks.com") | J16: 17/241, A- Gomti Nagar, Near Telephone Exchange, Agra Road, Aligarh - 202001, UP | K16: Premium designer handles, zinc alloy mortise sets, main entrance locks | L16: Dealer CRM + architect influencer tracking + sales automation | M16: Architects and interior designers recommend products but need dedicated project tracking | N16: Architect influencer portal to track specifications, sample dispatch, and incentives. | O16: 1. Uncontacted | P16: Medium | R16: =HYPERLINK("https://wa.me/919897148183?text=Namaste%20Sundeep%20Kumar%2C%20Badal%20here%20from%20EBM%20Solutions%20Aligarh.%20Regarding%20Tyler%20Locks%20%26%20Hardware%3A%20we%20specialize%20in%20Dealer%20CRM%20%2B%20architect%20influencer%20tracking%20%2B%20sales%20automation.%20Would%20you%20be%20open%20for%20a%20quick%205-min%20discussion%20this%20week%3F%20%28Reply%20STOP%20to%20opt%20out%29", "💬 Chat on WhatsApp")
A17: 13 | B17: Palam Locks & Hardware | C17: Palam Locks (Palam Security Products Co.) | D17: Siddhartha Bothra (Executive Director) | E17: Locks & Hardware | F17: +91 99970 99902 | G17: +91 93582 51981 / 0571-3298451 | H17: =HYPERLINK("mailto:palamlocks@gmail.com", "palamlocks@gmail.com") | I17: =HYPERLINK("http://www.palamlocks.com", "palamlocks.com") | J17: C-100, 101, Phase-I, UPSIDC, Talanagri, Ramghat Road, Aligarh - 202001, UP | K17: Heavy-duty padlocks, round locks, shutter locks, iron security systems | L17: Dealer network CRM + inventory/order analytics + warranty system | M17: Large dealer network ordering via calls and SMS causing billing delays | N17: WhatsApp automated dealer order assistant directly linked to inventory. | O17: 1. Uncontacted | P17: Medium | R17: =HYPERLINK("https://wa.me/919997099902?text=Namaste%20Siddhartha%20Bothra%2C%20Badal%20here%20from%20EBM%20Solutions%20Aligarh.%20Regarding%20Palam%20Locks%20%26%20Hardware%3A%20we%20specialize%20in%20Dealer%20network%20CRM%20%2B%20inventory/order%20analytics%20%2B%20warranty%20system.%20Would%20you%20be%20open%20for%20a%20quick%205-min%20discussion%20this%20week%3F%20%28Reply%20STOP%20to%20opt%20out%29", "💬 Chat on WhatsApp")
A18: 14 | B18: Victory Locks | C18: Victory Locks Private Limited | D18: Mohd. Izhar (Director) | E18: Locks & Hardware | F18: +91 99270 03453 | G18: +91 87917 71332 / +91 80438 68945 | H18: =HYPERLINK("mailto:info@victorylocks.shop", "info@victorylocks.shop") | I18: =HYPERLINK("http://victorylocks.shop", "victorylocks.shop") | J18: F-11-12, CDF Complex, Industrial Area, Anoopshahr Road, Aligarh - 202001, UP | K18: Pin cylinder locks, brass padlocks, export security hardware | L18: Export CRM + B2B lead generation + automated buyer nurturing | M18: Difficulty maintaining consistent follow-up with international wholesale buyers | N18: Multi-language drip email automation for Middle East and African export leads. | O18: 1. Uncontacted | P18: Medium | R18: =HYPERLINK("https://wa.me/919927003453?text=Namaste%20Mohd.%20Izhar%2C%20Badal%20here%20from%20EBM%20Solutions%20Aligarh.%20Regarding%20Victory%20Locks%3A%20we%20specialize%20in%20Export%20CRM%20%2B%20B2B%20lead%20generation%20%2B%20automated%20buyer%20nurturing.%20Would%20you%20be%20open%20for%20a%20quick%205-min%20discussion%20this%20week%3F%20%28Reply%20STOP%20to%20opt%20out%29", "💬 Chat on WhatsApp")
A19: 15 | B19: Asia Locks | C19: Asia Locks Manufacturing Co. | D19: Rajesh Sharma (General Manager) | E19: Locks & Hardware | F19: +91 98371 22340 | G19: +91 571 2401890 | H19: =HYPERLINK("mailto:asialocks.aligarh@gmail.com", "asialocks.aligarh@gmail.com") | I19: =HYPERLINK("https://www.indiamart.com/asialocks-aligarh/", "indiamart.com") | J19: Sarai Hakeem, Aligarh - 202001, UP | K19: Brass tumbler padlocks, iron locks, cycle locks, gate locks | L19: Digital catalogue + CRM + dealer management & wholesale tiering | M19: Managing varied wholesale discount tiers manually across multiple states | N19: Dynamic tier-pricing dealer portal with automated payment reminder links. | O19: 1. Uncontacted | P19: Medium | R19: =HYPERLINK("https://wa.me/919837122340?text=Namaste%20Rajesh%20Sharma%2C%20Badal%20here%20from%20EBM%20Solutions%20Aligarh.%20Regarding%20Asia%20Locks%3A%20we%20specialize%20in%20Digital%20catalogue%20%2B%20CRM%20%2B%20dealer%20management%20%26%20wholesale%20tiering.%20Would%20you%20be%20open%20for%20a%20quick%205-min%20discussion%20this%20week%3F%20%28Reply%20STOP%20to%20opt%20out%29", "💬 Chat on WhatsApp")
A20: 16 | B20: AVINASH MANUFACTURING INDUSTRY | C20: Avinash Manufacturing Industry | D20: Avinash Chandra (Proprietor) | E20: Locks & Hardware | F20: +91 78180 41325 | G20: +91 94121 78920 | H20: =HYPERLINK("mailto:avinashindustry@gmail.com", "avinashindustry@gmail.com") | I20: =HYPERLINK("https://www.indiamart.com/avinashmanufacturing/", "indiamart.com") | J20: Industrial Estate, Pala Road, Aligarh - 202001, UP | K20: Sheet metal components, lock parts, brass castings, builders hardware | L20: Production dashboard + OEM client workflow automation + job-work tracking | M20: Tracking custom tooling batches and delivery milestones for OEM lock brands | N20: Real-time job-work tracking dashboard to keep OEM clients updated automatically. | O20: 1. Uncontacted | P20: Medium | R20: =HYPERLINK("https://wa.me/917818041325?text=Namaste%20Avinash%20Chandra%2C%20Badal%20here%20from%20EBM%20Solutions%20Aligarh.%20Regarding%20AVINASH%20MANUFACTURING%20INDUSTRY%3A%20we%20specialize%20in%20Production%20dashboard%20%2B%20OEM%20client%20workflow%20automation%20%2B%20job-work%20tracking.%20Would%20you%20be%20open%20for%20a%20quick%205-min%20discussion%20this%20week%3F%20%28Reply%20STOP%20to%20opt%20out%29", "💬 Chat on WhatsApp")
A21: 17 | B21: Cent Metal Industries | C21: Cent Metal Industries | D21: Rakesh Gupta (Managing Partner) | E21: Locks & Hardware | F21: +91 96391 60269 | G21: +91 571 2740911 | H21: =HYPERLINK("mailto:centmetal@gmail.com", "centmetal@gmail.com") | I21: =HYPERLINK("https://www.tradeindia.com/centmetalindustries/", "tradeindia.com") | J21: C-14, Industrial Area, Tala Nagri, Aligarh - 202001, UP | K21: Non-ferrous metal hardware, die-cast handles, zinc components, brass extrusions | L21: Manufacturing analytics + inventory dispatch automation + raw material tracking | M21: Raw material price volatility impacting product quotation margins | N21: Smart cost estimation & dynamic quotation generator for metal fabricators. | O21: 1. Uncontacted | P21: Medium | R21: =HYPERLINK("https://wa.me/919639160269?text=Namaste%20Rakesh%20Gupta%2C%20Badal%20here%20from%20EBM%20Solutions%20Aligarh.%20Regarding%20Cent%20Metal%20Industries%3A%20we%20specialize%20in%20Manufacturing%20analytics%20%2B%20inventory%20dispatch%20automation%20%2B%20raw%20material%20tracking.%20Would%20you%20be%20open%20for%20a%20quick%205-min%20discussion%20this%20week%3F%20%28Reply%20STOP%20to%20opt%20out%29", "💬 Chat on WhatsApp")
A22: 18 | B22: Lakhdatar industries | Hardware manufacturer in Aligarh | stainless steel cabinet handles manufacturer | C22: Lakhdatar Industries | D22: Gaurav Varshney (Owner) | E22: Locks & Hardware | F22: +91 80571 17443 | G22: +91 90451 12345 | H22: =HYPERLINK("mailto:lakhdatarindustries@gmail.com", "lakhdatarindustries@gmail.com") | I22: =HYPERLINK("https://www.indiamart.com/lakhdatarindustries/", "indiamart.com") | J22: Nagla Mansingh, Sasni Gate, Aligarh - 202001, UP | K22: Stainless steel cabinet handles, kitchen hardware, concealed handles, main door pulls | L22: B2B CRM + interactive catalogue + interior designer sample request automation | M22: High demand for physical samples from modular kitchen contractors without lead capture | N22: Sample-kit request landing page with automated WhatsApp tracking for designers. | O22: 1. Uncontacted | P22: Medium | R22: =HYPERLINK("https://wa.me/918057117443?text=Namaste%20Gaurav%20Varshney%2C%20Badal%20here%20from%20EBM%20Solutions%20Aligarh.%20Regarding%20Lakhdatar%20industries%20%7C%20Hardware%20manufacturer%20in%20Aligarh%20%7C%20stainless%20steel%20cabinet%20handles%20manufacturer%3A%20we%20specialize%20in%20B2B%20CRM%20%2B%20interactive%20catalogue%20%2B%20interior%20designer%20sample%20request%20automation.%20Would%20you%20be%20open%20for%20a%20quick%205-min%20discussion%20this%20week%3F%20%28Reply%20STOP%20to%20opt%20out%29", "💬 Chat on WhatsApp")
A23: 19 | B23: DWARE PRODUCTS INDIA | C23: Dware Products India | D23: Deepak Kumar (Founder) | E23: Locks & Hardware | F23: +91 80770 35327 | G23: +91 571 2781450 | H23: =HYPERLINK("mailto:dwareproducts@gmail.com", "dwareproducts@gmail.com") | I23: =HYPERLINK("https://dwareproducts.com", "dwareproducts.com") | J23: Tala Nagri, Ramghat Road, Aligarh - 202001, UP | K23: Glass door fittings, patch fittings, shower hinges, floor springs | L23: B2B website + project lead CRM + architectural quote builder | M23: Commercial glass contractor projects require fast specification turnaround | N23: Instant glass hardware configurator & quote generator. | O23: 1. Uncontacted | P23: Medium | R23: =HYPERLINK("https://wa.me/918077035327?text=Namaste%20Deepak%20Kumar%2C%20Badal%20here%20from%20EBM%20Solutions%20Aligarh.%20Regarding%20DWARE%20PRODUCTS%20INDIA%3A%20we%20specialize%20in%20B2B%20website%20%2B%20project%20lead%20CRM%20%2B%20architectural%20quote%20builder.%20Would%20you%20be%20open%20for%20a%20quick%205-min%20discussion%20this%20week%3F%20%28Reply%20STOP%20to%20opt%20out%29", "💬 Chat on WhatsApp")
A24: 20 | B24: Home fit Exports | C24: Home Fit Exports | D24: Sunil Singhal (Managing Director) | E24: Locks & Hardware | F24: +91 98370 23411 | G24: +91 571 2970097 | H24: =HYPERLINK("mailto:info@homefitexports.com", "info@homefitexports.com") | I24: =HYPERLINK("http://www.homefitexports.com", "homefitexports.com") | J24: Delhi GT Road, Near Flyover, Aligarh - 202001, UP | K24: Export hardware, decorative ironmongery, curtain brackets, hooks, brass giftware | L24: Export lead management + buyer inquiry pipeline + international shipping dashboard | M24: Managing buyer inquiries from Canton Fair and international exhibitions in spreadsheets | N24: Trade-show lead digitization and automated post-fair follow-up sequences. | O24: 1. Uncontacted | P24: Medium | R24: =HYPERLINK("https://wa.me/919837023411?text=Namaste%20Sunil%20Singhal%2C%20Badal%20here%20from%20EBM%20Solutions%20Aligarh.%20Regarding%20Home%20fit%20Exports%3A%20we%20specialize%20in%20Export%20lead%20management%20%2B%20buyer%20inquiry%20pipeline%20%2B%20international%20shipping%20dashboard.%20Would%20you%20be%20open%20for%20a%20quick%205-min%20discussion%20this%20week%3F%20%28Reply%20STOP%20to%20opt%20out%29", "💬 Chat on WhatsApp")
A25: 21 | B25: K K Hospital | C25: K K Hospital & Heart Centre | D25: Dr. K.K. Sharma (Medical Director & Founder) | E25: Healthcare & Hospitals | F25: +91 90842 63669 | G25: +91 93687 77389 / 0571-2405600 | H25: =HYPERLINK("mailto:info@kkich.com", "info@kkich.com") | I25: =HYPERLINK("https://www.kkich.com", "kkich.com") | J25: Ramghat Road, Avas Vikas Colony, Aligarh - 202001, UP | K25: Multispeciality cardiac care, emergency ICU, diagnostics, surgical services | L25: Hospital CRM + workflow automation + patient WhatsApp lab report delivery | M25: Long wait lines and front-desk phone congestion for OPD booking and report collection | N25: Automated WhatsApp bot for OPD booking, doctor schedules, and digital report PDF dispatch. | O25: 1. Uncontacted | P25: Medium | R25: =HYPERLINK("https://wa.me/919084263669?text=Namaste%20Dr.%20K.K.%20Sharma%2C%20Badal%20here%20from%20EBM%20Solutions%20Aligarh.%20Regarding%20K%20K%20Hospital%3A%20we%20specialize%20in%20Hospital%20CRM%20%2B%20workflow%20automation%20%2B%20patient%20WhatsApp%20lab%20report%20delivery.%20Would%20you%20be%20open%20for%20a%20quick%205-min%20discussion%20this%20week%3F%20%28Reply%20STOP%20to%20opt%20out%29", "💬 Chat on WhatsApp")
A26: 22 | B26: Maxfort Multispeciality Hospital | C26: Maxfort Multispeciality Hospital | D26: Dr. Ankit Varshney (Medical Superintendent) | E26: Healthcare & Hospitals | F26: +91 98370 40699 | G26: +91 84455 09901 / 0571-2742300 | H26: =HYPERLINK("mailto:maxforthospital@gmail.com", "maxforthospital@gmail.com") | I26: =HYPERLINK("https://maxforthospitalaligarh.com", "maxforthospitalaligarh.com") | J26: Indraprastha Enclave, Near Kishanpur Tiraha, Ramghat Road, Aligarh - 202001, UP | K26: Orthopaedics, neurology, trauma center, obstetrics, diagnostic imaging | L26: Patient workflow + TPA insurance claim tracker + appointment CRM | M26: TPA cashless insurance paperwork causes discharge delays and patient frustration | N26: Real-time TPA insurance progress tracker and automated SMS discharge alerts. | O26: 1. Uncontacted | P26: Medium | R26: =HYPERLINK("https://wa.me/919837040699?text=Namaste%20Dr.%20Ankit%20Varshney%2C%20Badal%20here%20from%20EBM%20Solutions%20Aligarh.%20Regarding%20Maxfort%20Multispeciality%20Hospital%3A%20we%20specialize%20in%20Patient%20workflow%20%2B%20TPA%20insurance%20claim%20tracker%20%2B%20appointment%20CRM.%20Would%20you%20be%20open%20for%20a%20quick%205-min%20discussion%20this%20week%3F%20%28Reply%20STOP%20to%20opt%20out%29", "💬 Chat on WhatsApp")
A27: 23 | B27: Dheeraj Hospital | C27: Dheeraj Hospital & Trauma Centre | D27: Dr. Dheeraj Singh (Managing Director) | E27: Healthcare & Hospitals | F27: +91 99277 02625 | G27: +91 571 2508391 | H27: =HYPERLINK("mailto:dheerajhospitalaligarh@gmail.com", "dheerajhospitalaligarh@gmail.com") | I27: =HYPERLINK("https://dheerajhospital.com", "dheerajhospital.com") | J27: Near Gandhi Park Chauraha / Civil Lines, Aligarh - 202001, UP | K27: Emergency trauma, general surgery, ICU, inpatient medical care | L27: Inpatient admission CRM + pharmacy bill reconciliation + bed occupancy dashboard | M27: Manual record-keeping between admission desk, pharmacy, and central nursing station | N27: Centralized hospital occupancy and pharmacy billing coordination dashboard. | O27: 1. Uncontacted | P27: Medium | R27: =HYPERLINK("https://wa.me/919927702625?text=Namaste%20Dr.%20Dheeraj%20Singh%2C%20Badal%20here%20from%20EBM%20Solutions%20Aligarh.%20Regarding%20Dheeraj%20Hospital%3A%20we%20specialize%20in%20Inpatient%20admission%20CRM%20%2B%20pharmacy%20bill%20reconciliation%20%2B%20bed%20occupancy%20dashboard.%20Would%20you%20be%20open%20for%20a%20quick%205-min%20discussion%20this%20week%3F%20%28Reply%20STOP%20to%20opt%20out%29", "💬 Chat on WhatsApp")
A28: 24 | B28: SRD Logistics Pvt Ltd | C28: SRD Logistics Pvt Ltd | D28: Sanjay Agarwal (Managing Director) | E28: Logistics & Transport | F28: +91 80777 50891 | G28: +91 571 2404500 | H28: =HYPERLINK("mailto:info@srdlogistics.com", "info@srdlogistics.com") | I28: =HYPERLINK("https://srdlogistics.com", "srdlogistics.com") | J28: 13/9, Shah Kamal Rd, Gandhi Park, Aligarh - 202001, UP | K28: Pan-India freight logistics, full-truckload (FTL), warehousing, parcel transport | L28: Logistics customer portal + real-time dispatch tracking + automated consignment notes | M28: High volume of phone calls from lock and hardware manufacturers asking for shipment status | N28: WhatsApp automated tracking bot where clients enter LR number to get live status. | O28: 1. Uncontacted | P28: Medium | R28: =HYPERLINK("https://wa.me/918077750891?text=Namaste%20Sanjay%20Agarwal%2C%20Badal%20here%20from%20EBM%20Solutions%20Aligarh.%20Regarding%20SRD%20Logistics%20Pvt%20Ltd%3A%20we%20specialize%20in%20Logistics%20customer%20portal%20%2B%20real-time%20dispatch%20tracking%20%2B%20automated%20consignment%20notes.%20Would%20you%20be%20open%20for%20a%20quick%205-min%20discussion%20this%20week%3F%20%28Reply%20STOP%20to%20opt%20out%29", "💬 Chat on WhatsApp")
A29: 25 | B29: DEVANSH TRANSPORT COMPANY ALIGARH | C29: Devansh Transport Company | D29: Devansh Sharma (Proprietor) | E29: Logistics & Transport | F29: +91 89237 80044 | G29: +91 94123 45678 | H29: =HYPERLINK("mailto:devanshtransport@gmail.com", "devanshtransport@gmail.com") | I29: =HYPERLINK("https://devanshtransport.in", "devanshtransport.in") | J29: Delhi By Pass, Khair - Aligarh Road, Aligarh - 202001, UP | K29: Heavy freight transportation, industrial consignment delivery, Aligarh to Delhi/Punjab corridor | L29: Fleet order management + digital bilty generation + driver dispatch CRM | M29: Paper-based bilty and manual driver reconciliation causing billing disputes | N29: Digital mobile app for instant bilty creation and proof-of-delivery (POD) photo capture. | O29: 1. Uncontacted | P29: Medium | R29: =HYPERLINK("https://wa.me/918923780044?text=Namaste%20Devansh%20Sharma%2C%20Badal%20here%20from%20EBM%20Solutions%20Aligarh.%20Regarding%20DEVANSH%20TRANSPORT%20COMPANY%20ALIGARH%3A%20we%20specialize%20in%20Fleet%20order%20management%20%2B%20digital%20bilty%20generation%20%2B%20driver%20dispatch%20CRM.%20Would%20you%20be%20open%20for%20a%20quick%205-min%20discussion%20this%20week%3F%20%28Reply%20STOP%20to%20opt%20out%29", "💬 Chat on WhatsApp")
A30: 26 | B30: Ekkam International Hardware | C30: Ekkam International Hardware Pvt Ltd | D30: Jaswinder Singh (Director) | E30: Locks & Hardware | F30: +91 88003 09490 | G30: +91 11 45678900 | H30: =HYPERLINK("mailto:sales@ekkamhardware.com", "sales@ekkamhardware.com") | I30: =HYPERLINK("https://ekkamhardware.com", "ekkamhardware.com") | J30: Shop-1, Sharma Market, Udla Mod, GT Road, Aligarh - 202001, UP | K30: Zinc die-cast hardware, mortise handles, luxury cabinet handles, tower bolts | L30: B2B CRM + manufacturing analytics + dealer incentive loyalty engine | M30: Dealers lack a transparent rewards program for pushing high-margin handle designs | N30: QR-code scan dealer loyalty program and automated reward payout tracker. | O30: 1. Uncontacted | P30: Medium | R30: =HYPERLINK("https://wa.me/918800309490?text=Namaste%20Jaswinder%20Singh%2C%20Badal%20here%20from%20EBM%20Solutions%20Aligarh.%20Regarding%20Ekkam%20International%20Hardware%3A%20we%20specialize%20in%20B2B%20CRM%20%2B%20manufacturing%20analytics%20%2B%20dealer%20incentive%20loyalty%20engine.%20Would%20you%20be%20open%20for%20a%20quick%205-min%20discussion%20this%20week%3F%20%28Reply%20STOP%20to%20opt%20out%29", "💬 Chat on WhatsApp")
A31: 27 | B31: SRG Chemical Industries - Manufacturer & Exporters | C31: SRG Chemical Industries | D31: S.R. Gupta (Founder & Managing Partner) | E31: Chemical & Pharma | F31: +91 98370 54321 | G31: +91 571 2780555 | H31: =HYPERLINK("mailto:srgchemicals@gmail.com", "srgchemicals@gmail.com") | I31: =HYPERLINK("https://www.srgchemicals.com", "srgchemicals.com") | J31: Industrial Area, Tala Nagri, Ramghat Road, Aligarh - 202001, UP | K31: Electroplating chemicals, metal polishing compounds, degreasing solutions for lock factories | L31: Chemical batch inventory CRM + recurring B2B re-order automation + safety COA dispatch | M31: Local lock factories order chemicals unpredictably, leading to sudden stock-outs | N31: Predictive re-order reminder CRM that alerts lock factory purchasing managers when stock is low. | O31: 1. Uncontacted | P31: Medium | R31: =HYPERLINK("https://wa.me/919837054321?text=Namaste%20S.R.%20Gupta%2C%20Badal%20here%20from%20EBM%20Solutions%20Aligarh.%20Regarding%20SRG%20Chemical%20Industries%20-%20Manufacturer%20%26%20Exporters%3A%20we%20specialize%20in%20Chemical%20batch%20inventory%20CRM%20%2B%20recurring%20B2B%20re-order%20automation%20%2B%20safety%20COA%20dispatch.%20Would%20you%20be%20open%20for%20a%20quick%205-min%20discussion%20this%20week%3F%20%28Reply%20STOP%20to%20opt%20out%29", "💬 Chat on WhatsApp")
A32: 28 | B32: Swaroop Pharmaceuticals Pvt Ltd | C32: Swaroop Pharmaceuticals Pvt Ltd | D32: Vivek Swaroop (Director) | E32: Chemical & Pharma | F32: +91 94122 73556 | G32: 0571-2781101 / 2781104 | H32: =HYPERLINK("mailto:info@swarooppharma.com", "info@swarooppharma.com") | I32: =HYPERLINK("https://swarooppharma.com", "swarooppharma.com") | J32: A-10, Tala Nagri Industrial Estate, Ramghat Road, Aligarh - 202001, UP | K32: Allopathic pharmaceuticals, generic tablets, syrups, veterinary healthcare products | L32: Pharma distributor CRM + field sales representative tracking + expiry batch dashboard | M32: Field medical reps tracking chemist orders manually with delayed reporting | N32: Mobile field-sales app for MRs to log doctor visits, take distributor orders, and track targets. | O32: 1. Uncontacted | P32: Medium | R32: =HYPERLINK("https://wa.me/919412273556?text=Namaste%20Vivek%20Swaroop%2C%20Badal%20here%20from%20EBM%20Solutions%20Aligarh.%20Regarding%20Swaroop%20Pharmaceuticals%20Pvt%20Ltd%3A%20we%20specialize%20in%20Pharma%20distributor%20CRM%20%2B%20field%20sales%20representative%20tracking%20%2B%20expiry%20batch%20dashboard.%20Would%20you%20be%20open%20for%20a%20quick%205-min%20discussion%20this%20week%3F%20%28Reply%20STOP%20to%20opt%20out%29", "💬 Chat on WhatsApp")
A33: 29 | B33: Lemon Tree Hotel, Aligarh | C33: Lemon Tree Hotel, Aligarh | D33: General Manager & Banquet Sales Lead | E33: Hospitality & Hotels | F33: +91 73007 60288 | G33: +91 99117 01701 / 0571-2977777 | H33: =HYPERLINK("mailto:reservations.aligarh@lemontreehotels.com", "reservations.aligarh@lemontreehotels.com") | I33: =HYPERLINK("https://www.lemontreehotels.com", "lemontreehotels.com") | J33: Marris Road / Ramghat Road, Aligarh - 202001, UP | K33: Luxury rooms, banquet halls, corporate conference facilities, fine dining restaurant | L33: Banquet & wedding inquiry CRM + corporate booking automation + guest feedback bot | M33: High-value wedding and banquet inquiries arriving via phone/walk-ins are lost without automated follow-up | N33: Banquet lead management pipeline with automated proposal generation and deposit reminders. | O33: 1. Uncontacted | P33: Medium | R33: =HYPERLINK("https://wa.me/917300760288?text=Namaste%20General%20Manager%20%26%20Banquet%20Sales%20Lead%2C%20Badal%20here%20from%20EBM%20Solutions%20Aligarh.%20Regarding%20Lemon%20Tree%20Hotel%2C%20Aligarh%3A%20we%20specialize%20in%20Banquet%20%26%20wedding%20inquiry%20CRM%20%2B%20corporate%20booking%20automation%20%2B%20guest%20feedback%20bot.%20Would%20you%20be%20open%20for%20a%20quick%205-min%20discussion%20this%20week%3F%20%28Reply%20STOP%20to%20opt%20out%29", "💬 Chat on WhatsApp")
A34: 30 | B34: Fortune Park, Aligarh - Member ITC hotels’ group | C34: Fortune Park, Aligarh (ITC Hotel Group) | D34: General Manager / Director of Sales | E34: Hospitality & Hotels | F34: +91 92581 98371 | G34: +91 571 2755500 / +91 571 2755501 | H34: =HYPERLINK("mailto:reservations.fpag@fortunehotels.in", "reservations.fpag@fortunehotels.in") | I34: =HYPERLINK("https://www.fortunehotels.in", "fortunehotels.in") | J34: 3747/1, Near Agrasen Sewa Sadan, G.T. Road, Aligarh - 202001, UP | K34: Premium business hotel, banquet halls, boardroom facilities, corporate dining, catering | L34: Corporate B2B contract CRM + event proposal generator + guest loyalty analytics | M34: Local manufacturing executives host corporate buyers but corporate rates are manually negotiated | N34: Dedicated B2B corporate portal for Aligarh manufacturers to book corporate rooms and conferences. | O34: 1. Uncontacted | P34: Medium | R34: =HYPERLINK("https://wa.me/919258198371?text=Namaste%20General%20Manager%2C%20Badal%20here%20from%20EBM%20Solutions%20Aligarh.%20Regarding%20Fortune%20Park%2C%20Aligarh%20-%20Member%20ITC%20hotels%E2%80%99%20group%3A%20we%20specialize%20in%20Corporate%20B2B%20contract%20CRM%20%2B%20event%20proposal%20generator%20%2B%20guest%20loyalty%20analytics.%20Would%20you%20be%20open%20for%20a%20quick%205-min%20discussion%20this%20week%3F%20%28Reply%20STOP%20to%20opt%20out%29", "💬 Chat on WhatsApp")

Sheet Outreach Scripts & Guides
B2: COLD OUTREACH SCRIPTS & ACTION PLAYBOOK
B3: Direct templates distilled from deep-research-report.md
B6: WhatsApp / SMS Quick Pitch
B7: Hi [Name], Badal here from EBM Solutions in Aligarh. We help [Industry/Locks/Hospitals] in Aligarh automate their dealer inquiries and customer management. We built a solution that saved similar businesses 10+ hours a week and boosted inquiries by 40%. Could we do a quick 5-min call this week? Reply Y/N. (P.S. Reply STOP to opt-out)
B11: Cold Email Pitch
B12: Subject: Modernizing [Company Name]'s dealer & sales operations Hi [Decision Maker], I noticed [Company Name]'s strong reputation in Aligarh. We recently worked with peer firms to implement [ebm_opportunity], which cut inquiry response times and drove qualified distributor leads. Key advantage for [Company Name]: • [outreach_hook] Would you be open to a 10-minute introductory conversation this Thursday or Friday? Best regards, Badal Sharma | EBM Solutions Phone: [Your Phone] (Reply STOP to unsubscribe)
B16: LinkedIn Connection Note
B17: Hi [Name], I'm working with manufacturing and healthcare leaders in Uttar Pradesh to modernize their sales and dealer workflows. Would love to connect and share brief insights into digital catalog & CRM automation!
B21: Phone Call Script (Opening 30 Seconds)
B22: "Namaste [Name / Manager], this is Badal from EBM Solutions in Aligarh. I know you're busy so I'll be brief. We specifically assist [Industry, e.g. lock manufacturers / hospitals] in Aligarh with custom digital systems for [ebm_opportunity]. I wanted to see who on your team handles operations and sales systems?"

Sheet 30-60-90 Day Plan
B2: 30 / 60 / 90 DAY EXECUTION ROADMAP
B3: Phased timeline for data enrichment, multi-channel outreach, and closing deals
B5: Phase | C5: Timeframe | D5: Core Objective | E5: Key Action Items | F5: Success Target (KPI)
B6: Phase 1: Foundation & Audit | C6: Month 1 (Days 1–30) | D6: Data Enrichment & CRM Setup | E6: • Audit all 30 pre-loaded leads in this sheet • Fill in decision maker names, verified emails & LinkedIn profiles • Test WhatsApp & email outreach scripts with top 5 lock manufacturers • Ensure opt-out mechanics (STOP / Unsubscribe) are active | F6: 100% records enriched with direct contacts; 15 initial conversations initiated
B7: Phase 2: Active Multi-Channel Outreach | C7: Month 2 (Days 31–60) | D7: Pipeline Velocity & Pitches | E7: • Roll out WhatsApp & email sequences to all 30 target leads • Launch local Google Business Profile & local SEO for EBM • Conduct 8–10 discovery & demo calls • Send formal proposals for Dealer CRM / Custom Automation | F7: At least 6 formal proposals sent; 2 deals in final negotiation
B8: Phase 3: Deal Closing & Expansion | C8: Month 3 (Days 61–90) | D8: Closing & Referral Engine | E8: • Close initial 2–3 pilot accounts (Offer introductory retainer/pilot discount) • Implement client solutions & measure time/cost savings • Request testimonials and referrals to fellow Aligarh industrial units • Expand pipeline to 30 additional regional accounts | F8: 2–3 paying clients acquired; ₹1.5L+ in contracted revenue; 1 published case study
